tracking_lib/__init__.py
tracking_lib/config.py
tracking_lib/transaction.py
tracking_lib/adapters/__init__.py
tracking_lib/adapters/pubsub.py
tracking_lib/models/__init__.py
tracking_lib/models/transaction_status_update.py
tracking_lib/unit_tests/__init__.py
tracking_lib/unit_tests/cloud_function_test.py
tracking_lib/unit_tests/fastapi_app_test.py
tracking_lib/unit_tests/flask_app_test.py
tracking_lib/unit_tests/transaction_test.py
tracking_lib-0.1.30.dist-info/METADATA
tracking_lib-0.1.30.dist-info/WHEEL
tracking_lib-0.1.30.dist-info/top_level.txt
tracking_lib-0.1.30.dist-info/RECORD
