Metadata-Version: 2.1
Name: tracking-lib
Version: 0.1.30
Summary: A library for tracking transactions in Flask and FastAPI applications.
Home-page: https://github.com/thinkdigitalgroupprojectagora/team-moc-tracking-lib
Author: Damianos Damianidis
Author-email: damianosd@projectagora.com
Requires-Dist: fastapi >=0.103.1
Requires-Dist: Flask >=2.0.0
Requires-Dist: Werkzeug <3.0,>=2.2
Requires-Dist: google-cloud-pubsub >=2.18.4
